AUTHORS.rst
CONTRIBUTING.rst
HISTORY.rst
LICENSE
MANIFEST.in
README.rst
setup.cfg
setup.py
django_reinhardt.egg-info/PKG-INFO
django_reinhardt.egg-info/SOURCES.txt
django_reinhardt.egg-info/dependency_links.txt
django_reinhardt.egg-info/not-zip-safe
django_reinhardt.egg-info/requires.txt
django_reinhardt.egg-info/top_level.txt
docs/Makefile
docs/authors.rst
docs/conf.py
docs/contributing.rst
docs/history.rst
docs/index.rst
docs/installation.rst
docs/make.bat
docs/readme.rst
reinhardt/__init__.py
reinhardt/backends.py
reinhardt/decorators.py