Metadata-Version: 1.1
Name: django-reinhardt
Version: 0.2.0
Summary: Manage object permissions by defining methods in Django Model
Home-page: https://github.com/momamene/django-reinhardt
Author: Hyuntak Joo
Author-email: momamene@gmail.com
License: MIT license
Download-URL: https://github.com/momamene/django-reinhardt/tags
Keywords: django object logical permission auth authentication reinhardt
Platform: UNKNOWN
Classifier: Development Status :: 5 - Production/Stable
Classifier: Intended Audience :: Developers
Classifier: License :: OSI Approved :: MIT License
Classifier: Natural Language :: English
Classifier: Programming Language :: Python :: 3.3
Classifier: Programming Language :: Python :: 3.4
Classifier: Programming Language :: Python :: 3.5
